vtrplot/__init__.py
vtrplot/color_mappings.py
vtrplot/interp.py
vtrplot/sliced_models.py
vtrplot/vtr_image.py
vtrplot-0.3.4.dist-info/METADATA
vtrplot-0.3.4.dist-info/RECORD
vtrplot-0.3.4.dist-info/WHEEL
vtrplot-0.3.4.dist-info/top_level.txt
